<?xml version="1.0" encoding="utf-8" ?><dwsync><file name="alert.gif" server="ftp.themillrestaurant.com/www/" local="3283425846" remote="41989125744" /><file name="button.gif" server="ftp.themillrestaurant.com/www/" local="3283425846" remote="46284093040" /><file name="buttons.gif" server="ftp.themillrestaurant.com/www/" local="3284644246" remote="50579060336" /><file name="confirm.gif" server="ftp.themillrestaurant.com/www/" local="3283425846" remote="50579060336" /><file name="corners.gif" server="ftp.themillrestaurant.com/www/" local="3283425846" remote="50579060336" /><file name="drag.gif" server="ftp.themillrestaurant.com/www/" local="3284644246" remote="37694158448" /><file name="horizontal.gif" server="ftp.themillrestaurant.com/www/" local="3283425846" remote="63463962224" /><file name="vertical.gif" server="ftp.themillrestaurant.com/www/" local="3283425846" remote="54874027632" /><file name="alert.gif" server="lh35.dnsireland.com/public_html/" local="3283425846" remote="41990129064" /><file name="button.gif" server="lh35.dnsireland.com/public_html/" local="3283425846" remote="46285096360" /><file name="buttons.gif" server="lh35.dnsireland.com/public_html/" local="3284644246" remote="50580063656" /><file name="confirm.gif" server="lh35.dnsireland.com/public_html/" local="3283425846" remote="50580063656" /><file name="corners.gif" server="lh35.dnsireland.com/public_html/" local="3283425846" remote="50580063656" /><file name="drag.gif" server="lh35.dnsireland.com/public_html/" local="3284644246" remote="37695161768" /><file name="horizontal.gif" server="lh35.dnsireland.com/public_html/" local="3283425846" remote="63464965544" /><file name="vertical.gif" server="lh35.dnsireland.com/public_html/" local="3283425846" remote="54875030952" /></dwsync>