<?xml version="1.0" encoding="utf-8" ?><dwsync><file name="index.php" server="Macintosh HD/Users/hughlaw/Sites/The Mill Restaurant/" local="3331989709" remote="2204178559668986061" /><file name="contactus.php" server="Macintosh HD/Users/hughlaw/Sites/The Mill Restaurant/" local="3330938736" remote="2286318177116362608" /><file name="restaurant.php" server="Macintosh HD/Users/hughlaw/Sites/The Mill Restaurant/" local="3330953907" remote="2216681226646475443" /><file name="accommodation.php" server="ftp.marblewebdesign.com/public_html/clientDemos/themill/" local="3332143503" remote="2206073224362228108" /><file name="contactus.php" server="ftp.marblewebdesign.com/public_html/clientDemos/themill/" local="3332141822" remote="2206988911389733928" /><file name="googleeb2e4e6fe9d7bed2.html" server="ftp.marblewebdesign.com/public_html/clientDemos/themill/" local="3330935718" remote="119295071592" /><file name="index(demo).html" server="ftp.marblewebdesign.com/public_html/clientDemos/themill/" local="3328182299" remote="2206988911389733928" /><file name="index.php" server="ftp.marblewebdesign.com/public_html/clientDemos/themill/" local="3331989709" remote="2206988911389733928" /><file name="localarea.php" server="ftp.marblewebdesign.com/public_html/clientDemos/themill/" local="3332141344" remote="2206988911389733928" /><file name="messagesent.php" server="ftp.marblewebdesign.com/public_html/clientDemos/themill/" local="3331989046" remote="2206988911389733928" /><file name="navigation.php" server="ftp.marblewebdesign.com/public_html/clientDemos/themill/" local="3332582176" remote="2207362195587826420" /><file name="restaurant.php" server="ftp.marblewebdesign.com/public_html/clientDemos/themill/" local="3332587298" remote="2207362195587826420" /><file name="sendmail.php" server="ftp.marblewebdesign.com/public_html/clientDemos/themill/" local="3332143644" remote="2208296986629405188" /><file name="beautyatthemill.php" server="Macintosh HD/Users/hughlaw/Sites/The Mill Restaurant/" local="3331916995" remote="2179570647625696451" /><file name="localarea.php" server="Macintosh HD/Users/hughlaw/Sites/The Mill Restaurant/" local="3331991706" remote="395950856506845338" /><file name="beautyatthemill.php" server="ftp.marblewebdesign.com/public_html/clientDemos/themill/" local="3332583827" remote="2207362195587826420" /><file name="footer.php" server="ftp.marblewebdesign.com/public_html/clientDemos/themill/" local="3332582251" remote="2207362195587826420" /><file name="reviews.php" server="ftp.marblewebdesign.com/public_html/clientDemos/themill/" local="3332583737" remote="2207362195587826420" /><file name="googleeb2e4e6fe9d7bed2.html" server="ftp.themillrestaurant.com/www/" local="3330935718" remote="414193008544505844" /><file name="index(demo).html" server="ftp.themillrestaurant.com/www/" local="3328182299" remote="414193008544505844" /><file name="accommodation.php" server="ftp.themillrestaurant.com/www/" local="3334417184" remote="2257741423237344048" /><file name="beautyatthemill.php" server="ftp.themillrestaurant.com/www/" local="3334417178" remote="2257741423237344048" /><file name="contactus.php" server="ftp.themillrestaurant.com/www/" local="3334417172" remote="2257741423237344048" /><file name="footer.php" server="ftp.themillrestaurant.com/www/" local="3332582251" remote="414193008544505844" /><file name="index.php" server="ftp.themillrestaurant.com/www/" local="3334417192" remote="2257741423237344048" /><file name="localarea.php" server="ftp.themillrestaurant.com/www/" local="3334916104" remote="379869210463356932" /><file name="messagesent.php" server="ftp.themillrestaurant.com/www/" local="3334417161" remote="2257741423237344048" /><file name="navigation.php" server="ftp.themillrestaurant.com/www/" local="3334908136" remote="2168580479153252568" /><file name="restaurant.php" server="ftp.themillrestaurant.com/www/" local="3334417157" remote="2257741423237344048" /><file name="reviews.php" server="ftp.themillrestaurant.com/www/" local="3334916202" remote="382412587016833088" /><file name="sendmail.php" server="ftp.themillrestaurant.com/www/" local="3332143644" remote="414193008544505844" /><file name="robots.txt" server="ftp.themillrestaurant.com/www/" local="3334417602" remote="2163225805985885396" /><file name="sitemap.xml" server="ftp.themillrestaurant.com/www/" local="3334418022" remote="417869930046631544" /><file name="googleeb2e4e6fe9d7bed2.html" server="lh35.dnsireland.com/public_html/" local="3330935718" remote="392129246149903844" /><file name="index(demo).html" server="lh35.dnsireland.com/public_html/" local="3328182299" remote="392129246149903844" /><file name="accommodation.php" server="lh35.dnsireland.com/public_html/" local="3334417184" remote="392129246149903844" /><file name="beautyatthemill.php" server="lh35.dnsireland.com/public_html/" local="3334417178" remote="392129246149903844" /><file name="contactus.php" server="lh35.dnsireland.com/public_html/" local="3334417172" remote="392129246149903844" /><file name="footer.php" server="lh35.dnsireland.com/public_html/" local="3332582251" remote="392129246149903844" /><file name="index.php" server="lh35.dnsireland.com/public_html/" local="3334417192" remote="392129246149903844" /><file name="localarea.php" server="lh35.dnsireland.com/public_html/" local="3334916104" remote="392129246149903844" /><file name="messagesent.php" server="lh35.dnsireland.com/public_html/" local="3334417161" remote="392129246149903844" /><file name="navigation.php" server="lh35.dnsireland.com/public_html/" local="3334908136" remote="392129246149903844" /><file name="restaurant.php" server="lh35.dnsireland.com/public_html/" local="3334417157" remote="392129246149903844" /><file name="reviews.php" server="lh35.dnsireland.com/public_html/" local="3334916202" remote="392129246149903844" /><file name="sendmail.php" server="lh35.dnsireland.com/public_html/" local="3332143644" remote="392129246149903844" /><file name="robots.txt" server="lh35.dnsireland.com/public_html/" local="3334417602" remote="392129246149903844" /><file name="sitemap.xml" server="lh35.dnsireland.com/public_html/" local="3334418022" remote="392129246149903844" /></dwsync>